README.md
setup.py
exposer/__init__.py
exposer/actions.py
exposer/exposer.py
exposer/targets.py
exposer.egg-info/PKG-INFO
exposer.egg-info/SOURCES.txt
exposer.egg-info/dependency_links.txt
exposer.egg-info/top_level.txt
exposer/environments/Terminal256.py
exposer/environments/__init__.py
exposer/environments/exposable.py
exposer/environments/formatters.py
exposer/environments/parsers.py
exposer/environments/std.py
sample/__init__.py
sample/sample.py
test/__init__.py
test/exposer.py